yDataPrep/dp.py
yDataPrep-0.0.1.2.1.dist-info/LICENSE
yDataPrep-0.0.1.2.1.dist-info/METADATA
yDataPrep-0.0.1.2.1.dist-info/WHEEL
yDataPrep-0.0.1.2.1.dist-info/top_level.txt
yDataPrep-0.0.1.2.1.dist-info/RECORD
