Metadata-Version: 2.1
Name: yDataPrep
Version: 0.0.1.2.1
Summary: prepare your dataset for finetuning LLMs
Author: Shuvam Mandal
Author-email: shuvammandal121@gmail.com
License-File: LICENSE
Requires-Dist: datasets
Requires-Dist: transformers
Requires-Dist: pandas
Requires-Dist: tensorflow
